Metadata-Version: 2.1
Name: sparselayer-tensorflow
Version: 0.0.2
Summary: Tensorflow 2.X implementation of Sparse Layer.
Home-page: https://github.com/AryaAftab/sparselayer-tensorflow
Author: Arya Aftab
Author-email: arya.aftab@gmail.com
License: MIT
Keywords: deep learning,tensorflow,sparse layer
Platform: UNKNOWN
Classifier: Development Status :: 4 - Beta
Classifier: Intended Audience :: Developers
Classifier: Topic :: Scientific/Engineering :: Artificial Intelligence
Classifier: License :: OSI Approved :: MIT License
Classifier: Programming Language :: Python :: 3.6
License-File: LICENSE
